Workbook

Sheet problrm_statement
C9: Problem Statement — Personal Finance & Budget Analysis
C11: Problem Statement:
AZ12: onth
C14: Managing personal finances can be challenging when transaction data is available only in raw form. Without proper analysis, it is difficult to understand total income, spending levels, savings, major expense categories, and how income and expenses vary from month to month.

Sheet FinanceData
A1: Date | B1: Transaction Description | C1: Category | D1: Amount | E1: Type | F1: Month | G1: Year | H1: Signed_Amount
A2: 43832 | B2: Score each. | C2: Food & Drink | D2: 1485.69 | E2: Expense | F2: =TEXT(A2,"mmm") -> Jan | G2: =YEAR(A2) -> 2020 | H2: =IF(E2="Income",D2,-D2) -> -1485.69
A3: 43832 | B3: Quality throughout. | C3: Utilities | D3: 1475.58 | E3: Expense | F3: =TEXT(A3,"mmm") -> Jan | G3: =YEAR(A3) -> 2020 | H3: =IF(E3="Income",D3,-D3) -> -1475.58
A4: 43834 | B4: Instead ahead despite measure ago. | C4: Rent | D4: 1185.08 | E4: Expense | F4: =TEXT(A4,"mmm") -> Jan | G4: =YEAR(A4) -> 2020 | H4: =IF(E4="Income",D4,-D4) -> -1185.08
A5: 43835 | B5: Information last everything thank serve. | C5: Investment | D5: 2291 | E5: Income | F5: =TEXT(A5,"mmm") -> Jan | G5: =YEAR(A5) -> 2020 | H5: =IF(E5="Income",D5,-D5) -> 2291
A6: 43843 | B6: Future choice whatever from. | C6: Food & Drink | D6: 1126.88 | E6: Expense | F6: =TEXT(A6,"mmm") -> Jan | G6: =YEAR(A6) -> 2020 | H6: =IF(E6="Income",D6,-D6) -> -1126.88
A7: 43844 | B7: Benefit suggest page southern. | C7: Shopping | D7: 448.68 | E7: Expense | F7: =TEXT(A7,"mmm") -> Jan | G7: =YEAR(A7) -> 2020 | H7: =IF(E7="Income",D7,-D7) -> -448.68
A8: 43848 | B8: By two bad fall pick. | C8: Food & Drink | D8: 1520.03 | E8: Expense | F8: =TEXT(A8,"mmm") -> Jan | G8: =YEAR(A8) -> 2020 | H8: =IF(E8="Income",D8,-D8) -> -1520.03
A9: 43849 | B9: Court attorney product significant world. | C9: Other | D9: 3287 | E9: Income | F9: =TEXT(A9,"mmm") -> Jan | G9: =YEAR(A9) -> 2020 | H9: =IF(E9="Income",D9,-D9) -> 3287
A10: 43851 | B10: Herself law. | C10: Entertainment | D10: 1914.85 | E10: Expense | F10: =TEXT(A10,"mmm") -> Jan | G10: =YEAR(A10) -> 2020 | H10: =IF(E10="Income",D10,-D10) -> -1914.85
A11: 43855 | B11: Have decide environment. | C11: Rent | D11: 766.06 | E11: Expense | F11: =TEXT(A11,"mmm") -> Jan | G11: =YEAR(A11) -> 2020 | H11: =IF(E11="Income",D11,-D11) -> -766.06
A12: 43855 | B12: Play move each left establish. | C12: Health & Fitness | D12: 1211.41 | E12: Expense | F12: =TEXT(A12,"mmm") -> Jan | G12: =YEAR(A12) -> 2020 | H12: =IF(E12="Income",D12,-D12) -> -1211.41
A13: 43856 | B13: Range successful simply. | C13: Salary | D13: 1077.09 | E13: Expense | F13: =TEXT(A13,"mmm") -> Jan | G13: =YEAR(A13) -> 2020 | H13: =IF(E13="Income",D13,-D13) -> -1077.09
... A1501: 45655 | B1501: Pressure activity defense detail. | C1501: Other | D1501: 1480 | E1501: Income | F1501: =TEXT(A1501,"mmm") -> Dec | G1501: =YEAR(A1501) -> 2024 | H1501: =IF(E1501="Income",D1501,-D1501) -> 1480

Sheet Analysis
A1: FINANCIAL SUMMARY | B1: formula
A2: Total Income | B2: 1961281
A3: Total Expenses | B3: 1227194
A4: Net Savings | B4: =B2-B3 -> 734087
A5: Savings Rate | B5: =B4/B2 -> 0.37428956
A6: Total Transactions | B6: =COUNTA(FinanceData!A2:A1501) -> 1500
A7: Average Expense | B7: =AVERAGEIF(FinanceData!E2:E1501,"Expense",FinanceData!D2:D1501) -> 1004.2507
A8: Highest Expense | B8: =_xlfn.MAXIFS(FinanceData!D2:D1501,FinanceData!E2:E1501,"Expense") -> 1999.82

Sheet category_Analysis
A1: Type | B1: Expense
A3: Row Labels | B3: Sum of Amount
A4: Travel | B4: 169497.79
A5: Rent | B5: 162075.39
A6: Food & Drink | B6: 159493.39
A7: Salary | B7: 149053.55
A8: Entertainment | B8: 148165.47
A9: Shopping | B9: 146880.75
A10: Utilities | B10: 146833.97
A11: Health & Fitness | B11: 145194.06
A12: Grand Total | B12: 1227194.4

Sheet Monthly Analysis
A3: Sum of Amount | B3: Column Labels
A4: Row Labels | B4: Expense | C4: Income | D4: Grand Total
A5: Jan | B5: 112418.85 | C5: 79014 | D5: 191432.85
A6: Feb | B6: 97753.66 | C6: 70677 | D6: 168430.66
A7: Mar | B7: 100698.45 | C7: 87635 | D7: 188333.45
A8: Apr | B8: 92945.59 | C8: 45844 | D8: 138789.59
A9: May | B9: 105815.39 | C9: 48226 | D9: 154041.39
A10: Jun | B10: 111000.97 | C10: 51090 | D10: 162090.97
A11: Jul | B11: 116178.5 | C11: 57628 | D11: 173806.5
A12: Aug | B12: 110513.11 | C12: 51627 | D12: 162140.11
A13: Sep | B13: 102735.49 | C13: 65727 | D13: 168462.49
A14: Oct | B14: 88660.28 | C14: 63294 | D14: 151954.28
A15: Nov | B15: 107009.75 | C15: 64948 | D15: 171957.75
A16: Dec | B16: 81464.33 | C16: 48377 | D16: 129841.33
A17: Grand Total | B17: 1227194.4 | C17: 734087 | D17: 1961281.4

Sheet Dashboard
A1: PERSONAL FINANCE & BUDGET ANALYSIS DASHBOARD
B7: TOTAL INCOME TOTAL EXPENSES NET SAVINGS SAVINGS RATE
B8: =Analysis!B2 -> 1961281 | D8: =Analysis!B3 -> 1227194 | F8: =Analysis!B4 -> 734087
G9: =Analysis!B5 -> 0.37428956
B11: EXPENSE BY CATEGORY | R11: MONTHLY INCOME VS EXPENSE
B15: MONTHLY INCOME VS EXPENSE
